terrajinja/sbp/aws/iam_user_policy.py
terrajinja/sbp/aws/s3_bucket_versioning.py
terrajinja_sbp_aws-0.2.0.dist-info/LICENSE
terrajinja_sbp_aws-0.2.0.dist-info/METADATA
terrajinja_sbp_aws-0.2.0.dist-info/WHEEL
terrajinja_sbp_aws-0.2.0.dist-info/top_level.txt
terrajinja_sbp_aws-0.2.0.dist-info/RECORD
