Metadata-Version: 2.1
Name: terrajinja-sbp-aws
Version: 0.2.0
Summary: Terrajinja extension for automation using cdktf
Home-page: https://gitlab/terrajinja
Author: Terrajinja Team
Author-email: int-terrajinja@schubergphilis.com
License: MIT
Classifier: Development Status :: 4 - Beta
Classifier: Intended Audience :: Developers
Classifier: License :: OSI Approved :: MIT License
Classifier: Natural Language :: English
Classifier: Programming Language :: Python :: 3.11
License-File: LICENSE
Requires-Dist: cdktf-cdktf-provider-aws >=19.4.0
Requires-Dist: cdktf >=0.20.3
